Metadata-Version: 2.1
Name: clockify-seon-sspo-client
Version: 2.0.2
Summary: Responsible for send command to clockify job in sspo
Home-page: UNKNOWN
Author: Paulo Sergio dos Santo Junior
Author-email: paulossjuniort@gmail.com
License: UNKNOWN
Platform: UNKNOWN
Classifier: Programming Language :: Python :: 3
Classifier: License :: OSI Approved :: MIT License
Classifier: Operating System :: OS Independent
Requires-Dist: rabbitmqX
